{
  "name": "Khay úp cốc chữ nhật 5682",
  "code": "5682",
  "url": "https://vietnhatplastic.com/san-pham/san-pham-theo-nhom-1/khay-nhua/khay-up-coc-chu-nhat",
  "images": [
    "https://vietnhatplastic.com/Data/Sites/1/Product/4077/4-5682.jpg",
    "https://vietnhatplastic.com/Data/Sites/1/Product/4077/3-5682.jpg",
    "https://vietnhatplastic.com/Data/Sites/1/Product/4077/5-5682.jpg",
    "https://vietnhatplastic.com/Data/Sites/1/Product/4077/6-5682.jpg",
    "https://vietnhatplastic.com/Data/Sites/1/Product/4077/2-5682.jpg",
    "https://vietnhatplastic.com/Data/Sites/1/Product/4077/1-5682.jpg",
    "https://vietnhatplastic.com/Data/Sites/1/Product/4077/7-5682.jpg",
    "https://vietnhatplastic.com/Data/Sites/1/Product/4077/8-5682.jpg"
  ],
  "thumbnail": "https://vietnhatplastic.com/Data/Sites/1/Product/4077/4-5682.jpg",
  "badge": "Mới",
  "category": "khay-nhua",
  "page": 34,
  "dimensions": "D33.5xR23xC5 (cm)",
  "material": "Nhựa PP",
  "packaging": "15 cái/dây",
  "price": "Liên hệ",
  "colors": [
    "#e2e1dc",
    "#a8cdca",
    "#592f1f"
  ],
  "description": "Thông tin sản phẩm\nKhay úp cốc chữ nhật 5682 là sản phẩm khay đựng, úp cốc chén gọn gàng, ngay ngắn, thuận tiện sử dụng trong mọi gia đình, hàng quán. Sản phẩm được làm bằng chất liệu nhựa PP đảm bảo an toàn, bền bỉ, có thiết kế hai lớp cách nước tiện dụng, giúp vật dụng luôn khô ráo. Đặc biệt, bề mặt khay trên có nhiều lỗ chạy dọc, đẩy nhanh quá trình thoát nước."
}