{
  "name": "Khay đựng tài liệu 4T 5683-4",
  "code": "5683-4",
  "url": "https://vietnhatplastic.com/san-pham/san-pham-theo-nhom-1/khay-nhua/khay-dung-tai-lieu-4t",
  "images": [
    "https://vietnhatplastic.com/Data/Sites/1/Product/4223/2-5683-4-khay-%C4%91%E1%BB%B1ng-t%C3%A0i-li%E1%BB%87u-4t.png",
    "https://vietnhatplastic.com/Data/Sites/1/Product/4223/1-5683-4-khay-%C4%91%E1%BB%B1ng-t%C3%A0i-li%E1%BB%87u-4t.png",
    "https://vietnhatplastic.com/Data/Sites/1/Product/4223/4-5683-4-khay-%C4%91%E1%BB%B1ng-t%C3%A0i-li%E1%BB%87u-4t.png",
    "https://vietnhatplastic.com/Data/Sites/1/Product/4223/3-5683-4-khay-%C4%91%E1%BB%B1ng-t%C3%A0i-li%E1%BB%87u-4t.png"
  ],
  "thumbnail": "https://vietnhatplastic.com/Data/Sites/1/Product/4223/2-5683-4-khay-%C4%91%E1%BB%B1ng-t%C3%A0i-li%E1%BB%87u-4t.png",
  "badge": "Mới",
  "category": "khay-nhua",
  "page": 23,
  "dimensions": "D33xR25.5xC36 (cm)",
  "material": "Nhựa PP",
  "packaging": "8 bộ/thùng",
  "price": "Liên hệ",
  "colors": [
    "#979aa0",
    "#e2e1dc"
  ],
  "description": "Khay đựng tài liệu là một trong những sản phẩm văn phòng phổ biến dùng để phân loại, quản lý giấy tờ một cách hiệu quả và nhanh chóng. Với thiết kế thông minh, xếp nhiều tầng tiện dụng, khay đựng tài liệu không chỉ giúp bàn làm việc gọn gàng, ngăn nắp mà còn giúp bạn tăng hiệu suất làm việc và xử lý thông tin."
}