{
  "name": "Khay tròn thường 5661",
  "code": "5661",
  "url": "https://vietnhatplastic.com/san-pham/san-pham-theo-nhom-1/khay-nhua/khay-tron-thuong-4",
  "images": [
    "https://vietnhatplastic.com/Data/Sites/1/Product/1178/khay-tron-thuong-1.jpg",
    "https://vietnhatplastic.com/Data/Sites/1/Product/1178/khay-tron-thuong-2.jpg"
  ],
  "thumbnail": "https://vietnhatplastic.com/Data/Sites/1/Product/1178/khay-tron-thuong-1.jpg",
  "badge": "Mới",
  "category": "khay-nhua",
  "page": 123,
  "dimensions": "M28xĐ20.5xC3.5 (cm)",
  "material": "Nhựa PP",
  "packaging": "25 cái/dây",
  "price": "Liên hệ",
  "colors": [
    "#6387c5",
    "#c8270b"
  ],
  "description": "Thông tin sản phẩm\nKhay tròn thường 5661 là sản phẩm khay đựng, úp cốc chén \"quốc dân\" của nhiều gia đình Việt. Sản phẩm sử dụng chất liệu nhựa PP đảm bảo an toàn, dày dặn cùng thiết kế hai lớp cách nước tiện dụng. Đặc biệt, bề mặt khay trên có nhiều lỗ hình tim vừa đẩy nhanh quá trình thoát nước vừa tạo điểm nhấn thẩm mỹ nổi bật."
}