{
  "name": "Rổ bèo sâu 3220",
  "code": "3220",
  "url": "https://vietnhatplastic.com/san-pham/san-pham-theo-nhom-1/ro-ra-1/ro-beo-sau-5",
  "images": [
    "https://vietnhatplastic.com/Data/Sites/1/Product/1040/1-3220.jpg",
    "https://vietnhatplastic.com/Data/Sites/1/Product/1040/3-3220.jpg",
    "https://vietnhatplastic.com/Data/Sites/1/Product/1040/2-3220.jpg",
    "https://vietnhatplastic.com/Data/Sites/1/Product/1040/r%E1%BB%95-b%C3%A8o-3220,-3221.jpg"
  ],
  "thumbnail": "https://vietnhatplastic.com/Data/Sites/1/Product/1040/1-3220.jpg",
  "badge": "",
  "category": "ro-ra-1",
  "page": 93,
  "dimensions": "M26.5xĐ16xC9 (cm)",
  "material": "Nhựa PP",
  "packaging": "30 cái/bao",
  "price": "Liên hệ",
  "colors": [
    "#e2e1dc",
    "#ddb9b8",
    "#a8cdca"
  ],
  "description": "Thông tin sản phẩm\nRổ bèo sâu 3220 là bộ dụng cụ nhà bếp đa năng có ngoại hình đặc trưng với hình dáng bông hoa bắt mắt. Sản phẩm thiết kế hai lớp riêng biệt gồm 1 rổ nhiều lỗ thoát nước và 1 chậu đựng bên ngoài giúp thực phẩm mau ráo nước mà không làm ướt bếp. Sử dụng chất liệu nhựa PP an toàn, có độ bền cao, rổ bèo sâu giúp đáp ứng trọn vẹn nhu cầu của người nội trợ như dùng để đựng, rửa rau củ quả, chế biến thịt cá,…\n\n \n\nƯu điểm\n- Chất liệu nhựa PP nguyên sinh an toàn với thực phẩm, có độ bền cao\n- Có hai lớp rổ và chậu đựng riêng biệt giúp ráo nước thực phẩm mà không làm ướt bếp\n- Lớp rổ bên trong có nhiều lỗ phân bố đều từ nhỏ đến lớn giúp tăng khả năng thoát nước nhanh\n- Viền rổ và chậu dày dặn, nhẵn mịn, được cách điệu hình cánh hoa bắt mắt\n- Thiết kế lòng rổ, chậu sâu rộng, phù hợp để chứa đựng nhiều loại thực phẩm, đồ dùng\n- Bề mặt trơn bóng dễ dàng vệ sinh, hạn chế bám bẩn\n- Dễ dàng xếp chồng tiết kiệm diện tích\n- Màu sắc nhã nhặn, hiện đại phù hợp với nhiều không gian bếp\n\n\nHướng dẫn sử dụng\n- Dùng để rửa rau củ quả, chế biến thịt cá, đựng đồ dùng nhà bếp,...\n\nBảo quản\n- Tránh tiếp xúc với nguồn nhiệt cao hoặc ánh sáng mặt trời trực tiếp trong thời gian dài."
}