{
  "name": "Bình ủ nhiệt inox 4032",
  "code": "4032",
  "url": "https://vietnhatplastic.com/san-pham/san-pham-theo-nhom-1/san-pham-giu-nhiet-2/binh-u-nhiet-inox-11",
  "images": [
    "https://vietnhatplastic.com/Data/Sites/1/Product/396/14032.gif"
  ],
  "thumbnail": "https://vietnhatplastic.com/Data/Sites/1/Product/396/14032.gif",
  "badge": "Mới",
  "category": "san-pham-giu-nhiet-2",
  "page": 58,
  "dimensions": "M13xĐ14xC15.5 (cm)",
  "material": "Nhựa PP, Inox",
  "packaging": "30 cái/thùng",
  "price": "Liên hệ",
  "colors": [
    "#ddb9b8",
    "#b1ccde"
  ],
  "description": "Thông tin sản phẩm"
}