{
  "name": "Phích nước 3.2 3988",
  "code": "3988",
  "url": "https://vietnhatplastic.com/san-pham/san-pham-theo-nhom-1/san-pham-giu-nhiet-2/phich-nuoc-32l",
  "images": [
    "https://vietnhatplastic.com/Data/Sites/1/Product/4194/2-3988-ph%C3%ADch-n%C6%B0%E1%BB%9Bc-3.jpg",
    "https://vietnhatplastic.com/Data/Sites/1/Product/4194/3-3988-ph%C3%ADch-n%C6%B0%E1%BB%9Bc-3.jpg",
    "https://vietnhatplastic.com/Data/Sites/1/Product/4194/1-3988-ph%C3%ADch-n%C6%B0%E1%BB%9Bc-3.jpg",
    "https://vietnhatplastic.com/Data/Sites/1/Product/4194/4-3988-ph%C3%ADch-n%C6%B0%E1%BB%9Bc-3.jpg",
    "https://vietnhatplastic.com/Data/Sites/1/Product/4194/8-3988-ph%C3%ADch-n%C6%B0%E1%BB%9Bc-3.jpg",
    "https://vietnhatplastic.com/Data/Sites/1/Product/4194/7-3988-ph%C3%ADch-n%C6%B0%E1%BB%9Bc-3.jpg",
    "https://vietnhatplastic.com/Data/Sites/1/Product/4194/6-3988-ph%C3%ADch-n%C6%B0%E1%BB%9Bc-3.jpg",
    "https://vietnhatplastic.com/Data/Sites/1/Product/4194/5-3988-ph%C3%ADch-n%C6%B0%E1%BB%9Bc-3.jpg"
  ],
  "thumbnail": "https://vietnhatplastic.com/Data/Sites/1/Product/4194/2-3988-ph%C3%ADch-n%C6%B0%E1%BB%9Bc-3.jpg",
  "badge": "Mới",
  "category": "san-pham-giu-nhiet-2",
  "page": 25,
  "dimensions": "ø17xC42.5 (cm)",
  "material": "Nhựa PP, thủy tinh",
  "packaging": "1 cái/hộp, 9 hộp/thùng",
  "price": "Liên hệ",
  "colors": [
    "#e2e1dc",
    "#e9ddd5",
    "#a6b196"
  ],
  "description": "Phích nước 3.2 3988 có dung tích lớn giúp bạn dễ dàng trữ được nhiều nước nóng hơn đáp ứng tốt nhu cầu sử dụng hàng ngày của cả gia đình. Đây là sản phẩm tiện ích rất cần thiết trong cuộc sống hàng ngày, bạn có thể sử dụng nước nóng để pha trà, uống cà phê, pha sữa cho con,... một cách nhanh chóng và thuận tiện nhất.\nSản phẩm phù hợp dùng làm quà tặng đồng nghiệp, người thân và bạn bè trong những dịp lễ tết, kỉ niệm,..."
}