{
  "name": "Bật rác 2 ngăn 8020",
  "code": "8020",
  "url": "https://vietnhatplastic.com/san-pham/san-pham-theo-nhom-1/thung-rac-bat-rac/bat-rac-2-ngan",
  "images": [
    "https://vietnhatplastic.com/Data/Sites/1/Product/1313/bat-rac-2-ngan-3.jpg",
    "https://vietnhatplastic.com/Data/Sites/1/Product/1313/bat-rac-2-ngan-2.jpg",
    "https://vietnhatplastic.com/Data/Sites/1/Product/1313/bat-rac-2-ngan-1.jpg"
  ],
  "thumbnail": "https://vietnhatplastic.com/Data/Sites/1/Product/1313/bat-rac-2-ngan-3.jpg",
  "badge": "Mới",
  "category": "thung-rac-bat-rac",
  "page": 60,
  "dimensions": "D43xR32.5xC49.5 (cm)",
  "material": "Nhựa PP",
  "packaging": "1 cái/thùng",
  "price": "Liên hệ",
  "colors": [
    "#9c715d",
    "#a8cdca",
    "#e5b900",
    "#65544d"
  ],
  "description": "Bật rác 2 ngăn 8020 sử dụng hệ thống nắp bật chỉ bằng một lần nhấn chân nhẹ nhàng vào bàn đạp vô cùng tiện lợi. Với thiết kế chia hai ngăn đựng rác riêng biệt, bạn có thể dễ dàng sử dụng và phân loại rác hữu cơ và rác vô cơ, góp phần giữ gìn vệ sinh sạch sẽ và bảo vệ môi trường xung quanh."
}