{
  "name": "Ống đũa tròn 2766",
  "code": "2766",
  "url": "https://vietnhatplastic.com/san-pham/san-pham-theo-nhom-1/ong-dua-hop-giay-cam-coc/ong-dua-tron-2",
  "images": [
    "https://vietnhatplastic.com/Data/Sites/1/Product/1213/ong-dua-tron-2766.jpg"
  ],
  "thumbnail": "https://vietnhatplastic.com/Data/Sites/1/Product/1213/ong-dua-tron-2766.jpg",
  "badge": "",
  "category": "ong-dua-hop-giay-cam-coc",
  "page": 120,
  "dimensions": "M11.5xĐ14xC19 (cm)",
  "material": "Nhựa PP",
  "packaging": "50 cái/dây",
  "price": "Liên hệ",
  "colors": [
    "#c72808"
  ],
  "description": "Thông tin sản phẩm\nỐng đũa tròn 2766 là sản phẩm chuyên dụng dùng để lưu trữ và bảo quản đũa, thìa, muỗng,... Thân ống được thiết kế thoáng khí giúp dụng cụ bên trong luôn khô ráo, bên dưới có phần đế vững chãi, dễ dàng đặt trên bàn ăn hoặc bàn bếp của mọi gia đình, hàng quán. Đặc biệt, ống đũa tròn còn được tích hợp thêm 2 ngăn nhỏ đựng tăm tiện lợi giúp đáp ứng mọi nhu cầu sử dụng.\nƯu điểm\n- Chất liệu nhựa PP cao cấp đảm bảo an toàn, có độ bền cao\n- Thân ống đũa được làm thoáng khí giúp đồ dùng bên trong luôn khô ráo\n- Thiết kế đế vững chãi, dễ dàng đặt tại bàn ăn, bàn bếp\n- Có 2 lỗ bắt vít có thể cố định ống đũa chắc chắn trên tường\n- Tích hợp thêm 2 ống nhỏ đựng tăm tiện lợi bên cạnh\nHướng dẫn sử dụng\n- Dùng để bảo quản đũa, thìa, tăm,...\nBảo quản\n- Tránh tiếp xúc với nhiệt độ cao hoặc ánh sáng mặt trời trực tiếp trong thời gian dài."
}