{
  "name": "Bát tròn vân gỗ 1T9 6858",
  "code": "6858",
  "url": "https://vietnhatplastic.com/san-pham/san-pham-theo-nhom-1/au-bat-dia/bat-tron-van-go-1t9",
  "images": [
    "https://vietnhatplastic.com/Data/Sites/1/Product/4264/5-6858.jpg",
    "https://vietnhatplastic.com/Data/Sites/1/Product/4264/6-6858.jpg",
    "https://vietnhatplastic.com/Data/Sites/1/Product/4264/8-6858.jpg",
    "https://vietnhatplastic.com/Data/Sites/1/Product/4264/7-6858.jpg",
    "https://vietnhatplastic.com/Data/Sites/1/Product/4264/4-6858.jpg",
    "https://vietnhatplastic.com/Data/Sites/1/Product/4264/3-6858.jpg",
    "https://vietnhatplastic.com/Data/Sites/1/Product/4264/2-6858.jpg",
    "https://vietnhatplastic.com/Data/Sites/1/Product/4264/1-6858.jpg"
  ],
  "thumbnail": "https://vietnhatplastic.com/Data/Sites/1/Product/4264/5-6858.jpg",
  "badge": "Mới",
  "category": "au-bat-dia",
  "page": 20,
  "dimensions": "M19x Đ9.5 x C9.3 (cm)",
  "material": "Nhựa ABS",
  "packaging": "5 cái/túi, 20 cái/thùng",
  "price": "Liên hệ",
  "colors": [
    "#54161d",
    "#c2b5ad"
  ],
  "description": "Bát tròn vân gỗ được làm từ nhựa ABS nguyên sinh có độ bền cao, hạn chế rơi vỡ và an toàn khi đựng thực phẩm. Bát có màu sắc nhã nhặn, bên ngoài có những đường vân gỗ tự nhiên tạo điểm nhấn bắt mắt và tăng tính thẩm mỹ cho bàn ăn. Sản phẩm phù hợp với nhiều không gian sử dụng khác nhau, dùng để đựng mì, canh, salad, hoặc các món trộn,..."
}