{
  "name": "Đĩa phíp xoắn 1211",
  "code": "1211",
  "url": "https://vietnhatplastic.com/san-pham/san-pham-theo-nhom-1/au-bat-dia/dia-phip-xoan-1211",
  "images": [
    "https://vietnhatplastic.com/Data/Sites/1/Product/4456/%C4%91%C4%A9a-xo%E1%BA%AFn.jpg"
  ],
  "thumbnail": "https://vietnhatplastic.com/Data/Sites/1/Product/4456/%C4%91%C4%A9a-xo%E1%BA%AFn.jpg",
  "badge": "Mới",
  "category": "au-bat-dia",
  "page": 4,
  "dimensions": "M18xĐ9xC3 (cm)",
  "material": "Nhựa ABS",
  "packaging": "160 cái/thùng",
  "price": "Liên hệ",
  "colors": [
    "#000000",
    "#d9dbe6"
  ],
  "description": ""
}