{
  "name": "Đĩa phíp vuông 1210-3",
  "code": "1210-3",
  "url": "https://vietnhatplastic.com/san-pham/san-pham-theo-nhom-1/au-bat-dia/dia-phip-vuong-57",
  "images": [
    "https://vietnhatplastic.com/Data/Sites/1/Product/4231/7-1210-3-nham.jpg",
    "https://vietnhatplastic.com/Data/Sites/1/Product/4231/6-1210-3-nham.jpg",
    "https://vietnhatplastic.com/Data/Sites/1/Product/4231/5-1210-3-nham.jpg",
    "https://vietnhatplastic.com/Data/Sites/1/Product/4231/4-1210-3-nham.jpg",
    "https://vietnhatplastic.com/Data/Sites/1/Product/4231/3-1210-3-nham.jpg",
    "https://vietnhatplastic.com/Data/Sites/1/Product/4231/2-1210-3-nham.jpg",
    "https://vietnhatplastic.com/Data/Sites/1/Product/4231/1-1210-3-nham.jpg"
  ],
  "thumbnail": "https://vietnhatplastic.com/Data/Sites/1/Product/4231/7-1210-3-nham.jpg",
  "badge": "Mới",
  "category": "au-bat-dia",
  "page": 22,
  "dimensions": "D20.6xR20.6xC2.3 (cm)",
  "material": "Nhựa ABS",
  "packaging": "60 cái/thùng",
  "price": "Liên hệ",
  "colors": [
    "#111111",
    "#a1867b",
    "#f4f5f6"
  ],
  "description": "Đĩa phíp vuông là sản phẩm đĩa nhựa phíp được sử dụng phổ biến ở hàng quán bởi sự tiện lợi, đa dạng kích thước và dễ dàng vệ sinh sau mỗi lần sử dụng. Bên cạnh mẫu đĩa phíp vuông trơn thường thấy, hiện tại Nhựa Việt Nhật ra mắt thêm sản phẩm có bề mặt nhám lì tinh tế, hiện đại giúp món ăn trở nên ngon miệng và hấp dẫn hơn."
}