{
  "name": "Kệ indo to 2T 5532-2",
  "code": "5532-2",
  "url": "https://vietnhatplastic.com/san-pham/san-pham-theo-nhom-1/ke-gio-mac-ao-1/ke-indo-to-2t-6",
  "images": [
    "https://vietnhatplastic.com/Data/Sites/1/Product/1095/ke-indo-to-2T-5532.jpg"
  ],
  "thumbnail": "https://vietnhatplastic.com/Data/Sites/1/Product/1095/ke-indo-to-2T-5532.jpg",
  "badge": "Mới",
  "category": "ke-gio-mac-ao-1",
  "page": 81,
  "dimensions": "D54xR34.5xC39 (cm)",
  "material": "Nhựa PP",
  "packaging": "",
  "price": "Liên hệ",
  "colors": [
    "#d70000",
    "#6387c5"
  ],
  "description": "Kệ indo to 2T 5532-2 là sản phẩm kệ đựng đồ \"quốc dân\" của nhiều gia đình Việt bởi khả năng đựng đồ đa năng, tiện lợi, có thể sử dụng ở nhiều vị trí khác nhau trong nhà. Kệ indo được làm bằng nhựa nguyên sinh có độ bền bỉ cao, thiết kế chồng tầng gọn gàng, lắp ráp dễ dàng và kết cấu chịu lực tốt. Ngoài ra, sản phẩm được trang bị thêm ống đựng tiện lợi bên cạnh giúp bạn bảo quản các vật dụng nhỏ gọn như đũa thìa, dao kéo,..."
}